{
    "appKeys": {},
    "capabilities": [
        "configurable"
    ],
    "companyName": "alexisgeoffrey",
    "enableMultiJS": false,
    "longName": "5moreminutes",
    "projectType": "native",
    "resources": {
        "media": [
            {
                "file": "images/icon",
                "menuIcon": true,
                "name": "app_icon",
                "targetPlatforms": null,
                "type": "bitmap"
            }
        ]
    },
    "sdkVersion": "3",
    "shortName": "5moreminutes",
    "targetPlatforms": [
        "aplite",
        "basalt",
        "chalk"
    ],
    "uuid": "b3dd40a5-5fc1-4b0d-a015-4a329f9999eb",
    "versionLabel": "1.0",
    "watchapp": {
        "watchface": false
    }
}
